moda/dataprep/__init__.py
moda/dataprep/create_dataset.py
moda/dataprep/data_reader.py
moda/dataprep/utils.py
moda/evaluators/__init__.py
moda/evaluators/eval.py
moda/evaluators/eval_all_models.py
moda/evaluators/metrics.py
moda/models/__init__.py
moda/models/azure_ad.py
moda/models/lstm_anomaly.py
moda/models/ma_seasonal_model.py
moda/models/stl_model.py
moda/models/trend_detector.py
moda/models/twitter/__init__.py
moda/models/twitter/anomaly_detect_ts.py
moda/models/twitter/anomaly_detect_vec.py
moda/models/twitter/dynamic_cusum.py
moda/models/twitter/twitter_trendiness_detector.py
moda-0.3.3.dist-info/LICENSE
moda-0.3.3.dist-info/METADATA
moda-0.3.3.dist-info/WHEEL
moda-0.3.3.dist-info/top_level.txt
moda-0.3.3.dist-info/RECORD
