Metadata-Version: 2.1
Name: moda
Version: 0.3.3
Summary: Tools for analyzing trending topics
Home-page: https://www.github.com/omri374/moda
Author: Omri Mendels
Author-email: omri.mendels@microsoft.com
License: UNKNOWN
Platform: UNKNOWN
Requires-Dist: numpy
Requires-Dist: pandas
Requires-Dist: stldecompose
Requires-Dist: statsmodels (==0.10.2)
Requires-Dist: comet-ml
Requires-Dist: requests
Requires-Dist: matplotlib
Requires-Dist: pytest
Requires-Dist: scikit-learn (==0.23.0)
Requires-Dist: pytest-cov
